{
  "date": "2026-04-02",
  "query": "Finsehytta",
  "results": [
    {
      "title": "Bergens Tidende",
      "url": "https://www.facebook.com/bergenstidende/posts/%C3%A5pen-for-alle/1264657919215302/",
      "body_text": "Bergens Tidende - (Åpen for alle)",
      "summary": "Artikkelen inneholder informasjon fra Bergens Tidende som er åpen for alle.",
      "category": "annet",
      "sentiment": "nøytral"
    },
    {
      "title": "DNT Oslo og Omegn – Turer, Friluftsliv, Hyttetur og ...",
      "url": "https://www.dnt.no/dnt-der-du-er/dnt-oslo-og-omegn/",
      "body_text": "DNT Oslo og Omegn – Turer, Friluftsliv, Hyttetur og Naturopplevelser\nHopp til hovedinnhold\nTilbake\nFoto: Marius Dalseg Sætre\nDNT Oslo og Omegn\nSett som favoritt\nFjern som favoritt\nDNT Oslo og Omegn\nBli med oss ut i marka, på fjorden eller til fjells!\nVi jobber med å legge til rette for at flest mulig skal få gode naturopplevelser. Foreningen har ansvar for merking og vedlikehold av turstier, hyttedrift og organisering av turer og aktiviteter.\nSe også\nSe aktivitetskalender\nSe aktivitetskalender\nFinn deg en hytte i Oslomarka\nFinn deg en hytte i Oslomarka\nBli frivillig i DNT\nBli frivillig i DNT\nBli DNT-medlem\nBli DNT-medlem\nKommende aktiviteter:\nVis alle i DNTs aktivitetskalender\nÅpne aktivitetskalender\nSe flere aktiviteter i DNTs aktivitetskalender\nVis alle\nVis alle i DNTs aktivitetskalender\nVåre lokallag\nDenne medlemsforeningen i DNT har flere lokallag. De arrangerer mange ulike turer og har sine egne aktive turgrupper. Besøk deres egen hjemmeside for mer info og følg dem gjerne på sosiale medier.\nDNT der du er\nDNT der du er\nAsker Turlag\nBærum Turlag\nEidsvoll Turlag\nGjerdrum Turlag\nLillestrøm og Rælingen Turlag\nLørenskog Turlag\nNannestad Turlag\nNesodden Turlag\nNordre Follo Turlag\nTurkameratene Nittedal Turlag\nUllensaker Turlag\nVestby Turlag\nÅs Turlag\nFrogn Turlag\nSlik merkes stiene i Oslomarka\nSlik merkes stiene i Oslomarka\nI skogene rundt Oslo er det 2800 km blåmerkede stier. Arbeidet med skilting og merking av blåstiene har vært gjennomført på dugnad helt siden dette arbeidet startet på slutten av 1920-tallet.\nLes videre\nTakk til våre samarbeidspartnere",
      "summary": "DNT Oslo og Omegn tilbyr turer, hytteturer og naturopplevelser, og arbeider med merking av stier, hyttedrift og organisering av aktiviteter. De har flere lokallag som arrangerer turer og aktiviteter i Oslomarka og omegn.",
      "category": "turisme",
      "sentiment": "positiv"
    },
    {
      "title": "Wetter Finse: 16 Tage Trend",
      "url": "https://www.wetter.com/wetter_aktuell/wettervorhersage/16_tagesvorhersage/norwegen/finse/NO3157520.html",
      "body_text": "Wetter Finse: 16 Tage Trend | wetter.com\nWetter Finse 16 Tage Trend\nHeute\n03.04.\nMorgen\n04.04.\n3 Tage\nWochenende\n7 Tage\n16 Tage\nRegenradar\nPollenflug\nRückblick\nFr 03.04.\n-5°\n-11°\n90 %\nSa 04.04.\n-5°\n-6°\n90 %\nSo 05.04.\n-3°\n-7°\n90 %\nMo 06.04.\n-4°\n-6°\n90 %\nDi 07.04.\n-2°\n-5°\n30 %\nMi 08.04.\n10°\n-3°\n90 %\nDo 09.04.\n9°\n5°\n0 %\n16-Tage Ausblick\n×\nMondmission Artemis II: Crew hat Erdumlaufbahn verlassen\nMondmission Artemis II: Crew hat Erdumlaufbahn verlassen\nJetzt Video ansehen\nFinnland-Wetter\njetzt 21:56.\nAktuelles Wetter in\nFinse\n-5°C\nSchneefall\nFeedback geben\nPollenflug ansehen\nFeedback zum aktuellem Wetter\nHilf uns, die Wetterdaten zu verbessern, indem Du die aktuellen Bedingungen an Deinem Standort beschreibst.\n                    Wir zeigen:\n-5°C\nSchneefall\nWie ist das Wetter bei Dir?\nWie warm ist es bei Dir?\nWir zeigen:\nSchneefall\nWir zeigen:\n-5°C\nWird richtig angezeigt\nsonnig\nwolkig\nRegen\nSchnee\nNebel\nGewitter\nWird richtig angezeigt\nsonnig\nleicht bewölkt\nwolkig\nbedeckt\nRegen\nSchnee\nNebel\nGewitter\nWird richtig angezeigt\nleichter Regen\nmäßiger Regen\nstarker Regen\nsonnig\nwolkig\nSchnee\nNebel\nGewitter\nWird richtig angezeigt\nleichter Schneefall\nmäßiger Schneefall\nstarker Schneefall\nsonnig\nleicht bewölkt\nRegen\nNebel\nGewitter\nEs ist wärmer\nWird richtig angezeigt\nEs ist kälter\nWeiter\nFertig\nDerzeit liegen keine Wetterwarnungen für Finse vor.\nWetter Finse 16 Tage Trend\nKalender\nListe\nFR 03.04.\n-5°\n/ -11°\nZeitweise Schneefall und windig\n90 %\n                                                    | 10,2 l/m²\n3 h\ngefühlt -11° / -16°\nSA 04.04.\n-5°\n/ -6°\nZeitweise leichter Schneefall, teils sonnig und windig\n90 %\n                                                    | 1,3 l/m²\n6 h\ngefühlt -10° / -16°\nSO 05.04.\n-3°\n/ -7°\nAnhaltender Schneefall und stürmisch\n90 %\n                                                    | 14,8 l/m²\n0 h\ngefühlt -6° / -17°\nMO 06.04.\n-4°\n/ -6°\nÜberwiegend leichter Schneefall und stürmisch\n90 %\n                                                    | 2,0 l/m²\n6 h\ngefühlt -13° / -18°\nDI 07.04.\n-2°\n/ -5°\nSonne und Wolken\n30 %\n9 h\ngefühlt -2° / -10°\nMI 08.04.\n10°\n/ -3°\nTeils sonnig, vereinzelt leichter Schneefall\n90 %\n                                                    | 1,9 l/m²\n5 h\ngefühlt 8° / -8°\nDO 09.04.\n9°\n/ 5°\nViel Sonne, leicht bewölkt und windig\n0 %\n10 h\ngefühlt 7° / 1°\nFR 10.04.\n10°\n/ 5°\nViel Sonne, leicht bewölkt und windig\n0 %\n9 h\ngefühlt 8° / 0°\nSA 11.04.\n10°\n/ 5°\nViel Sonne, leicht bewölkt und windig\n0 %\n9 h\ngefühlt 8° / 1°\nSO 12.04.\n8°\n/ 4°\nViel Sonne, leicht bewölkt\n0 %\n9 h\ngefühlt 6° / 0°\nMO 13.04.\n8°\n/ -4°\nViel Sonne, leicht bewölkt\n0 %\n9 h\ngefühlt 6° / -8°\nDI 14.04.\n0°\n/ -6°\nSonne und Wolken\n10 %\n5 h\ngefühlt -2° / -10°\nMI 15.04.\n-2°\n/ -6°\nStark bewölkt\n20 %\n0 h\ngefühlt -6° / -11°\nDO 16.04.\n-1°\n/ -8°\nWechselnd bewölkt, wenig Sonne\n20 %\n3 h\ngefühlt -4° / -13°\nFR 17.04.\n0°\n/ -7°\nSonne und Wolken\n0 %\n10 h\ngefühlt 0° / -11°\nSA 18.04.\n1°\n/ -5°\nSonne und Wolken\n0 %\n6 h\ngefühlt -1° / -8°\nFR 03.04.\nZeitweise Schneefall und windig\n-5°\n/ -11°\ngefühlt\n-11°/ -16°\n90 %\n10,2 cm\nSO\n16 km/h\nBöen 47 km/h\n06:48 Uhr\n20:17 Uhr\n3 h\nUV-Index\nAbnehmender Mond\nMorgens\n06 - 12 Uhr\n-9°\n/ -11°\nSonne und Wolken\n20 %\n0 l/m²\nSO\n8 km/h\nMittags\n12 - 18 Uhr\n-6°\n/ -8°\nZeitweise Schneefall und windig\n90 %\n4,0 cm\nSO\n20 km/h\nBöen 45 km/h\nAbends\n18 - 22 Uhr\n-5°\n/ -5°\nAnhaltender Schneefall und windig\n90 %\n6,2 cm\nSO\n24 km/h\nBöen 47 km/h\nNachts\n22 - 06 Uhr\n-5°\n/ -6°\nAnhaltender Schneefall und windig\n90 %\n6,2 cm\nW\n16 km/h\nBöen 46 km/h\nZur Tagesvorhersage\nSA 04.04.\nZeitweise leichter Schneefall, teils sonnig und windig\n-5°\n/ -6°\ngefühlt\n-10°/ -16°\n90 %\n1,3 cm\nW\n33 km/h\nBöen 62 km/h\n06:45 Uhr\n20:20 Uhr\n6 h\nUV-Index\nAbnehmender Mond\nMorgens\n06 - 12 Uhr\n-5°\n/ -6°\nAnhaltend leichter Schneefall und windig\n90 %\n0,9 cm\nW\n37 km/h\nBöen 62 km/h\nMittags\n12 - 18 Uhr\n-5°\n/ -5°\nZeitweise leichter Schneefall, teils sonnig und windig\n90 %\n0,4 cm\nW\n37 km/h\nBöen 58 km/h\nAbends\n18 - 22 Uhr\n-6°\n/ -6°\nÜberwiegend wolkig und windig\n40 %\n0 l/m²\nW\n19 km/h\nBöen 44 km/h\nNachts\n22 -",
      "summary": "Artikkelen gir en 16-dagers værmelding for Finse, med detaljer om temperatur, snøfall og vindforhold. Den inkluderer også informasjon om soltimer og UV-indeks.",
      "category": "vær",
      "sentiment": "nøytral"
    }
  ]
}